google/shopping/merchant_reviews/__init__.py
google/shopping/merchant_reviews/gapic_version.py
google/shopping/merchant_reviews/py.typed
google/shopping/merchant_reviews_v1beta/__init__.py
google/shopping/merchant_reviews_v1beta/gapic_metadata.json
google/shopping/merchant_reviews_v1beta/gapic_version.py
google/shopping/merchant_reviews_v1beta/py.typed
google/shopping/merchant_reviews_v1beta/services/__init__.py
google/shopping/merchant_reviews_v1beta/services/merchant_reviews_service/__init__.py
google/shopping/merchant_reviews_v1beta/services/merchant_reviews_service/async_client.py
google/shopping/merchant_reviews_v1beta/services/merchant_reviews_service/client.py
google/shopping/merchant_reviews_v1beta/services/merchant_reviews_service/pagers.py
google/shopping/merchant_reviews_v1beta/services/merchant_reviews_service/transports/__init__.py
google/shopping/merchant_reviews_v1beta/services/merchant_reviews_service/transports/base.py
google/shopping/merchant_reviews_v1beta/services/merchant_reviews_service/transports/grpc.py
google/shopping/merchant_reviews_v1beta/services/merchant_reviews_service/transports/grpc_asyncio.py
google/shopping/merchant_reviews_v1beta/services/merchant_reviews_service/transports/rest.py
google/shopping/merchant_reviews_v1beta/services/merchant_reviews_service/transports/rest_base.py
google/shopping/merchant_reviews_v1beta/services/product_reviews_service/__init__.py
google/shopping/merchant_reviews_v1beta/services/product_reviews_service/async_client.py
google/shopping/merchant_reviews_v1beta/services/product_reviews_service/client.py
google/shopping/merchant_reviews_v1beta/services/product_reviews_service/pagers.py
google/shopping/merchant_reviews_v1beta/services/product_reviews_service/transports/__init__.py
google/shopping/merchant_reviews_v1beta/services/product_reviews_service/transports/base.py
google/shopping/merchant_reviews_v1beta/services/product_reviews_service/transports/grpc.py
google_shopping_merchant_reviews-0.4.0.dist-info/licenses/LICENSE
google_shopping_merchant_reviews-0.4.0.dist-info/METADATA
google_shopping_merchant_reviews-0.4.0.dist-info/WHEEL
google_shopping_merchant_reviews-0.4.0.dist-info/top_level.txt
google_shopping_merchant_reviews-0.4.0.dist-info/RECORD
